{
  "resources": [
    {
      "type": "texture",
      "bindingName": "albedoTex",
      "resourcePath": "../data/processed/textures/trees/tree01/branch_A.texture"
    },
    {
      "type": "texture",
      "bindingName": "tangentTex",
      "resourcePath": "../data/processed/textures/trees/tree01/branch_N.texture"
    },
    {
      "type": "texture",
      "bindingName": "roughnessTex",
      "resourcePath": "../data/processed/textures/trees/tree01/branch_R.texture"
    },
    {
      "type": "texture",
      "bindingName": "metallicTex",
      "resourcePath": "../data/processed/textures/black.texture"
    },
    {
      "type": "mesh",
      "bindingName": "",
      "resourcePath": "../data/processed/meshes/trees/tree01/tree01Leaves.model"
    },
    {
      "type": "constantBuffer",
      "bindingName": "materialConfig",
      "resourcePath": "",
      "uniformContent": [
        { "name" : "albedoTexConfig", "type": "vec4", "value":  [1.0,1.0,0.0,0.0] },
        { "name" : "normalTexConfig", "type": "vec4", "value":  [1.0,1.0,0.0,0.0] },
        { "name" : "metallicTexConfig", "type": "vec4", "value":  [1.0,1.0,0.0,0.0] },
        { "name" : "roughnessTexConfig", "type": "vec4", "value":  [1.0,1.0,0.0,0.0] },
        { "name": "metalRoughMult", "type": "vec2", "value": [ 1.0, 1.0 ]}
      ] 
    }
  ],
  "queue" :  ["forward"],
  "type" : ["forwardPhongPSO"],
  "isStatic": true 
}
