{
 "type":  "RASTER",
 "inputLayout":  "deferredNull",
 "globalRootSignature": "../data/rs/SSSSSEffect_RS.json",
  "VS": "fullScreenQuadVS",
  "PS":  "SSSSSEffectPS",
  "rasterState":  "default",
  "blendState": "default",
  "depthStencilState": "custom",
  "depthStencilStateConfig": {
    "depthEnabled" :  false,
    "depthFunc": "GREATER",
    "stencilEnabled": true,
    "stencilFailOp" :  "KEEP",
    "stencilDepthFailOp" :  "KEEP",
    "stencilPassOp": "KEEP",
    "stencilFunc" : "EQUAL" 
  },
  "sampleMask":  "max",
  "topologyType": "triangle",
  "renderTargets": 1,
  "rtvFormats": [ "DXGI_FORMAT_R16G16B16A16_FLOAT" ],
  "sampleDescCount": 1,
  "sampleDescQuality":  0,
  "dsvFormat": "DXGI_FORMAT_D32_FLOAT_S8X24_UINT"
}

    
